clusterx/__init__.py
clusterx/clusters_selector.py
clusterx/config.py
clusterx/correlations.py
clusterx/cross_validation.py
clusterx/derivative_structures.py
clusterx/lattices.py
clusterx/model.py
clusterx/parent_lattice.py
clusterx/structure.py
clusterx/structure_selector.py
clusterx/structures_set.py
clusterx/super_cell.py
clusterx/symmetry.py
clusterx/utils.py
clusterx/visualization.py
clusterx/calculators/__init__.py
clusterx/calculators/emt.py
clusterx/cli/__init__.py
clusterx/cli/commands.py
clusterx/cli/main.py
clusterx/cli/plot_clusters.py
clusterx/cli/spacegroup.py
clusterx/cli/test.py
clusterx/clusters/__init__.py
clusterx/clusters/cluster.py
clusterx/clusters/clusters_pool.py
clusterx/estimators/__init__.py
clusterx/estimators/estimator_factory.py
clusterx/io/__init__.py
clusterx/io/atat.py
clusterx/io/formats.py
clusterx/test/__init__.py
clusterx/test/test_clathrate_mc.py
clusterx/test/test_cluster.py
clusterx/test/test_cluster_correlations.py
clusterx/test/test_cluster_expansion.py
clusterx/test/test_cluster_orbit.py
clusterx/test/test_cluster_orbit2.py
clusterx/test/test_clusters_generation.py
clusterx/test/test_clusters_selector.py
clusterx/test/test_clusters_selector_lasso.py
clusterx/test/test_concentration.py
clusterx/test/test_emt2_calculator.py
clusterx/test/test_folders.py
clusterx/test/test_get_all_hnf.py
clusterx/test/test_get_unique_supercells.py
clusterx/test/test_is_nary.py
clusterx/test/test_lattice_representation.py
clusterx/test/test_metropolis.py
clusterx/test/test_parent_lattice_creation.py
clusterx/test/test_predict_swap.py
clusterx/test/test_structure_selector.py
clusterx/test/test_structures_set.py
clusterx/test/test_wanglandau.py
clusterX-2.1.0rc3.dist-info/COPYING
clusterX-2.1.0rc3.dist-info/LICENSE.txt
clusterX-2.1.0rc3.dist-info/METADATA
clusterX-2.1.0rc3.dist-info/WHEEL
clusterX-2.1.0rc3.dist-info/entry_points.txt
clusterX-2.1.0rc3.dist-info/top_level.txt
clusterX-2.1.0rc3.dist-info/RECORD
